LICENSE
MANIFEST.in
README.rst
setup.py
certifi_icpbr/__init__.py
certifi_icpbr/cacert.pem
certifi_icpbr/core.py
certifi_icpbr/version.py
certifi_icpbr.egg-info/PKG-INFO
certifi_icpbr.egg-info/SOURCES.txt
certifi_icpbr.egg-info/dependency_links.txt
certifi_icpbr.egg-info/not-zip-safe
certifi_icpbr.egg-info/requires.txt
certifi_icpbr.egg-info/top_level.txt
tests/test_icpbr.py